opentelemetry/instrumentation/writer/__init__.py
opentelemetry/instrumentation/writer/config.py
opentelemetry/instrumentation/writer/event_emitter.py
opentelemetry/instrumentation/writer/event_models.py
opentelemetry/instrumentation/writer/span_utils.py
opentelemetry/instrumentation/writer/utils.py
opentelemetry/instrumentation/writer/version.py
opentelemetry_instrumentation_writer-0.51.1.dist-info/METADATA
opentelemetry_instrumentation_writer-0.51.1.dist-info/WHEEL
opentelemetry_instrumentation_writer-0.51.1.dist-info/entry_points.txt
opentelemetry_instrumentation_writer-0.51.1.dist-info/RECORD
