Metadata-Version: 2.4
Name: opentelemetry-instrumentation-writer
Version: 0.51.1
Summary: OpenTelemetry Writer instrumentation
Project-URL: Repository, https://github.com/traceloop/openllmetry/tree/main/packages/opentelemetry-instrumentation-writer
Author-email: Yan Tolstoy <yan.talstoi@writer.com>, "Writer, Inc." <dev-feedback@writer.com>
License-Expression: Apache-2.0
Requires-Python: <4,>=3.10
Requires-Dist: opentelemetry-api<2,>=1.38.0
Requires-Dist: opentelemetry-instrumentation>=0.59b0
Requires-Dist: opentelemetry-semantic-conventions-ai>=0.4.11
Requires-Dist: opentelemetry-semantic-conventions>=0.59b0
Provides-Extra: instruments
Requires-Dist: writer; extra == 'instruments'
